paramath/__init__.py
paramath/__main__.py
paramath/cli.py
paramath_lang-2.2.6.dist-info/licenses/LICENSE
paramath_lang-2.2.6.dist-info/METADATA
paramath_lang-2.2.6.dist-info/WHEEL
paramath_lang-2.2.6.dist-info/entry_points.txt
paramath_lang-2.2.6.dist-info/top_level.txt
paramath_lang-2.2.6.dist-info/RECORD
