Metadata-Version: 2.4
Name: paramath-lang
Version: 2.2.6
Summary: A differentiable programming language for continuous computation
Author: Kaemori Yozzan
License-Expression: MIT
Project-URL: Homepage, https://github.com/kaemori/paramath
Project-URL: Repository, https://github.com/kaemori/paramath
Project-URL: Issues, https://github.com/kaemori/paramath/issues
Project-URL: Documentation, https://github.com/kaemori/paramath/blob/main/docs/paramath_docs.md
Classifier: Programming Language :: Python :: 3
Classifier: Operating System :: OS Independent
Classifier: Topic :: Scientific/Engineering :: Mathematics
Classifier: Intended Audience :: Science/Research
Requires-Python: >=3.8
License-File: LICENSE
Provides-Extra: sympy
Requires-Dist: sympy>=1.10; extra == "sympy"
Requires-Dist: tqdm>=4.64; extra == "sympy"
Dynamic: license-file
